{
  "version": 1,
  "editor": "wokwi",
  "parts": [
    {
      "type": "board-esp32-devkit-c-v4",
      "id": "esp1",
      "top": 175.8,
      "left": 225.8,
      "rotate": 270,
      "attrs": {}
    },
    {
      "type": "board-ssd1306",
      "id": "oled1",
      "top": 60,
      "left": 229.27,
      "attrs": { "i2cAddress": "0x3c" }
    },
    {
      "type": "wokwi-dht22",
      "id": "dht1",
      "top": 266.34,
      "left": 544.8,
      "rotate": 90,
      "attrs": {}
    },
    {
      "type": "wokwi-resistor",
      "id": "res1",
      "top": 374.94,
      "left": 408.1,
      "attrs": { "value": "220" }
    },
    {
      "type": "wokwi-led",
      "id": "led1",
      "top": 377.34,
      "left": 523.5,
      "rotate": 90,
      "attrs": { "color": "red", "label": "Canh bao nuoc" }
    },
    {
      "type": "wokwi-resistor",
      "id": "res2",
      "top": 454.94,
      "left": 408.1,
      "attrs": { "value": "220" }
    },
    {
      "type": "wokwi-led",
      "id": "led2",
      "top": 444.54,
      "left": 513.9,
      "rotate": 90,
      "attrs": { "color": "blue", "label": "Nhiet do" }
    },
    {
      "type": "wokwi-resistor",
      "id": "res3",
      "top": 524.94,
      "left": 408.1,
      "attrs": { "value": "220" }
    },
    {
      "type": "wokwi-led",
      "id": "led3",
      "top": 514.94,
      "left": 513.9,
      "rotate": 90,
      "attrs": { "color": "yellow", "label": "Do man" }
    },
    {
      "type": "wokwi-resistor",
      "id": "res4",
      "top": 594.94,
      "left": 408.1,
      "attrs": { "value": "220" }
    },
    {
      "type": "wokwi-led",
      "id": "led4",
      "top": 584.94,
      "left": 513.9,
      "rotate": 90,
      "attrs": { "color": "white", "label": "MAY BOM" }
    },
    { "type": "wokwi-potentiometer", "id": "pot1", "top": 149.14, "left": 438.8, "attrs": {} },
    {
      "type": "wokwi-hc-sr04",
      "id": "ultrasonic1",
      "top": 279.44,
      "left": 10,
      "rotate": 270,
      "attrs": {}
    }
  ],
  "connections": [
    [ "esp1:GND.1", "oled1:GND", "magenta", [ "v0" ] ],
    [ "esp1:3V3", "oled1:VCC", "red", [ "v0" ] ],
    [ "esp1:21", "oled1:SDA", "blue", [ "v0" ] ],
    [ "esp1:22", "oled1:SCL", "yellow", [ "v0" ] ],
    [ "esp1:GND.2", "dht1:GND", "blue", [ "v0" ] ],
    [ "esp1:3V3", "dht1:VCC", "red", [ "v0" ] ],
    [ "esp1:4", "dht1:SDA", "green", [ "v0" ] ],
    [ "esp1:5", "res1:1", "orange", [ "v0" ] ],
    [ "res1:2", "led1:A", "orange", [ "v0" ] ],
    [ "esp1:GND.3", "led1:C", "black", [ "v0" ] ],
    [ "esp1:18", "res2:1", "cyan", [ "v0" ] ],
    [ "res2:2", "led2:A", "cyan", [ "v0" ] ],
    [ "esp1:GND.3", "led2:C", "black", [ "v0" ] ],
    [ "esp1:19", "res3:1", "green", [ "v0" ] ],
    [ "res3:2", "led3:A", "green", [ "v0" ] ],
    [ "esp1:GND.3", "led3:C", "black", [ "v0" ] ],
    [ "esp1:2", "res4:1", "white", [ "v0" ] ],
    [ "res4:2", "led4:A", "white", [ "v0" ] ],
    [ "esp1:GND.3", "led4:C", "black", [ "v0" ] ],
    [ "esp1:GND.1", "pot1:GND", "#8f4814", [ "v0" ] ],
    [ "esp1:3V3", "pot1:VCC", "red", [ "v0" ] ],
    [ "esp1:34", "pot1:SIG", "purple", [ "v0" ] ],
    [ "esp1:GND.2", "ultrasonic1:GND", "limegreen", [ "v0" ] ],
    [ "esp1:5V", "ultrasonic1:VCC", "red", [ "v0" ] ],
    [ "esp1:12", "ultrasonic1:TRIG", "green", [ "v0" ] ],
    [ "esp1:14", "ultrasonic1:ECHO", "yellow", [ "v0" ] ]
  ],
  "dependencies": {}
}